{
    "NomRencontre" : "R03 et R04 - Modèle en boîtes et positionnement",
    "Exemples" : [
        {
            "NomDossier" : "Exemple 01 - Le modèle en boîte (border, margin, padding, height, width, box-sizing)",
            "LienDepotGit" : "https://github.com/420-2W6-EM/exemple-r03-r04-n01-modele-boite.git"
        },
        {
            "NomDossier" : "Exemple 02 - La disposition des éléments (inline, block, block, inline-block)",
            "LienDepotGit" : "https://github.com/420-2W6-EM/exemple-r03-r04-n02-disposition-element.git"
        },
        {
            "NomDossier" : "Exemple 03 - Transformer une liste UL en menu (étude de cas)",
            "LienDepotGit" : "https://github.com/420-2W6-EM/exemple-r03-r04-n03-transform-ul-vers-menu.git"
        },
        {
            "NomDossier" : "Exemple 04 - Positionnement (static, relatif, left, right, bottom, top)",
            "LienDepotGit" : "https://github.com/420-2W6-EM/exemple-r03-r04-n04-position-static-relatif.git"
        },
        {
            "NomDossier" : "Exemple 05 - Positionnement (absolute, fixed, z-index, left, right, bottom, top)",
            "LienDepotGit" : "https://github.com/420-2W6-EM/exemple-r03-r04-n05-position-absolute-fixed.git"
        },
        {
            "NomDossier" : "Exemple 06 - Animer les propriétés CSS et exemple de sélecteur pseudo-class (hover)",
            "LienDepotGit" : "https://github.com/420-2W6-EM/exemple-r03-r04-n06-animer-propriete-css.git"
        },
        {
            "NomDossier" : "Exemple 07 - Sélecteurs et priorité des régles CSS (sans vidéo)",
            "LienDepotGit" :"https://github.com/420-2W6-EM/exemple-r03-r04-n07-selecteur-css-et-priorite.git"
        }
    ],
    "Exercices" : [ 
        {
            "NomDossier" : "Exercice 00 - Exercices en ligne avec autocorrection",
            "FichiersRajouter": [
                {
                    "destination_filename" : "Instructions.docx",
                    "source_full_file_path" : "R03 et R04 - Modèle en boîtes et positionnement et TP1/Exercice 0 - Instructions - w3school.docx"
                }
            ]
        },
        {
            "NomDossier" : "Exercice 1 - Afficher correctement les territoires des châteaux",
            "LienDepotGit" : "https://github.com/420-2W6-EM/exercice-r03-r04-n01-territoire-chateau.git",
            "FichiersRajouter": [
                {
                    "destination_filename" : "Instructions.docx",
                    "source_full_file_path" : "R03 et R04 - Modèle en boîtes et positionnement et TP1/Exercice 1 - Instructions - Châteaux.docx"
                }
            ]
        },
        {
            "NomDossier" : "Exercice 2 - La propriété Display",
            "LienDepotGit" : "https://github.com/420-2W6-EM/exercice-r03-r04-n02-propriete-display.git",
            "FichiersRajouter": [
                {
                    "destination_filename" : "Instructions.docx",
                    "source_full_file_path" : "R03 et R04 - Modèle en boîtes et positionnement et TP1/Exercice 2 - Instructions - Display.docx"
                }
            ]
        },
        {
            "NomDossier" : "Exercice 3 - Le positionnement relatif et la troisième dimension (z-index)",
            "LienDepotGit" : "https://github.com/420-2W6-EM/exercice-r03-r04-n03-position-relatif-zindex.git",
            "FichiersRajouter": [
                {
                    "destination_filename" : "Instructions.docx",
                    "source_full_file_path" : "R03 et R04 - Modèle en boîtes et positionnement et TP1/Exercice 3 - Instructions - Position relatif z-index.docx"
                }
            ]
        },
        {
            "NomDossier" : "Exercice 4 - Les positionnements absolute et fixed",
            "LienDepotGit" : "https://github.com/420-2W6-EM/exercice-r03-r04-n04-position-absolute-fixed.git",
            "FichiersRajouter": [
                {
                    "destination_filename" : "Instructions.docx",
                    "source_full_file_path" : "R03 et R04 - Modèle en boîtes et positionnement et TP1/Exercice 4 - Instructions - Position absolute et fixed.docx"
                }
            ]
        },
        {
            "NomDossier" : "Exercice 5 - Appliquer une transition sur des propriétés",
            "LienDepotGit" : "https://github.com/420-2W6-EM/exercice-r03-r04-n05-transform-proprietes.git",
            "FichiersRajouter": [
                {
                    "destination_filename" : "Instructions.docx",
                    "source_full_file_path" : "R03 et R04 - Modèle en boîtes et positionnement et TP1/Exercice 5 - Instructions - transition propriété CSS.docx"
                }
            ]
        }
    ],
    "ConfigurationGlobal" : {
        "FichiersSupprimer" : ["README.md", ".gitignore", "cd-values.yml", "dockerfile"],
        "DossiersSupprimer" : [".github", ".git"],
        "FichiersRajouterRacineZip": [
                {
                    "versions" : ["ExemplesVersionDepart", "ExemplesVersionSolution"],
                    "destination_filename" : "R03 et R04 - Liens vidéos notions.url",
                    "source_full_file_path" : "R03 et R04 - Modèle en boîtes et positionnement et TP1/R03 et R04 - Liens vidéos notions.url"
                },
                {
                    "versions" : ["ExemplesVersionDepart", "ExemplesVersionSolution", "ExercicesVersionDepart", "ExercicesVersionSolution"],
                    "destination_filename" : "R03 et R04 - Liens utiles.docx",
                    "source_full_file_path" : "R03 et R04 - Modèle en boîtes et positionnement et TP1/R03 et R04 - Liens utiles.docx"
                },
                {
                    "versions" : ["ExemplesVersionDepart", "ExemplesVersionSolution"],
                    "destination_filename" : "R03 et R04 - Introduction à HTML et CSS.pptx",
                    "source_full_file_path" : "R03 et R04 - Modèle en boîtes et positionnement et TP1/R03 et R04 - Modèle en boîtes et positionnement.pptx"
                }
            ]
    }
}